{
  "placeholderImages": [
    {
      "id": "partner-1",
      "description": "Proxmox Gold Partner logo",
      "imageUrl": "/images/partners/proxmox-gold-partner-logo.png",
      "imageHint": "company logo"
    },
    {
      "id": "partner-2",
      "description": "Dell Partner logo",
      "imageUrl": "/images/partners/dell.png",
      "imageHint": "company logo"
    },
    {
      "id": "partner-3",
      "description": "Microsoft Partner logo",
      "imageUrl": "/images/partners/microsoft.png",
      "imageHint": "company logo"
    },
    {
      "id": "partner-4",
      "description": "Bitdefender Partner logo",
      "imageUrl": "/images/partners/bitdefender.jpg",
      "imageHint": "company logo"
    },
    {
      "id": "partner-5",
      "description": "VEEAM Partner logo",
      "imageUrl": "/images/partners/veeam.png",
      "imageHint": "company logo"
    },
    {
      "id": "partner-6",
      "description": "Google Cloud Partner logo",
      "imageUrl": "https://images.unsplash.com/photo-1562783912-21ad31ee2a83?crop=entropy&cs=tinysrgb&fit=max&fm=jpg&ixid=M3w3NDE5ODJ8MHwxfHNlYXJjaHwyfHxjb21wYW55JTIwbG9nb3xlbnwwfHx8fDE3NjU0MjkwNDJ8MA&ixlib=rb-4.1.0&q=80&w=1080",
      "imageHint": "company logo"
    },
    {
      "id": "client-1",
      "description": "Global Net logo",
      "imageUrl": "https://images.unsplash.com/photo-1619551734325-81aaf323686c?crop=entropy&cs=tinysrgb&fit=max&fm=jpg&ixid=M3w3NDE5ODJ8MHwxfHNlYXJjaHw1fHxjb21wYW55JTIwbG9nb3xlbnwwfHx8fDE3NjU0MjkwNDJ8MA&ixlib=rb-4.1.0&q=80&w=1080",
      "imageHint": "company logo"
    },
    {
      "id": "client-2",
      "description": "Pioneer Labs logo",
      "imageUrl": "https://images.unsplash.com/photo-1622465911368-72162f8da3e2?crop=entropy&cs=tinysrgb&fit=max&fm=jpg&ixid=M3w3NDE5ODJ8MHwxfHNlYXJjaHw0fHxjb21wYW55JTIwbG9nb3xlbnwwfHx8fDE3NjU0MjkwNDJ8MA&ixlib=rb-4.1.0&q=80&w=1080",
      "imageHint": "company logo"
    },
    {
      "id": "client-3",
      "description": "Visionary Tech logo",
      "imageUrl": "https://images.unsplash.com/photo-1687523327554-fa9f50423489?crop=entropy&cs=tinysrgb&fit=max&fm=jpg&ixid=M3w3NDE5ODJ8MHwxfHNlYXJjaHw5fHxjb21wYW55JTIwbG9nb3xlbnwwfHx8fDE3NjU0MjkwNDJ8MA&ixlib=rb-4.1.0&q=80&w=1080",
      "imageHint": "company logo"
    },
    {
      "id": "client-4",
      "description": "Synergy Inc logo",
      "imageUrl": "https://images.unsplash.com/photo-1549924231-f129b911e442?crop=entropy&cs=tinysrgb&fit=max&fm=jpg&ixid=M3w3NDE5ODJ8MHwxfHNlYXJjaHw3fHxjb21wYW55JTIwbG9nb3xlbnwwfHx8fDE3NjU0MjkwNDJ8MA&ixlib=rb-4.1.0&q=80&w=1080",
      "imageHint": "company logo"
    },
    {
      "id": "client-5",
      "description": "Fusion Works logo",
      "imageUrl": "https://images.unsplash.com/photo-1687523327554-fa9f50423489?crop=entropy&cs=tinysrgb&fit=max&fm=jpg&ixid=M3w3NDE5ODJ8MHwxfHNlYXJjaHw5fHxjb21wYW55JTIwbG9nb3xlbnwwfHx8fDE3NjU0MjkwNDJ8MA&ixlib=rb-4.1.0&q=80&w=1080",
      "imageHint": "company logo"
    },
    {
      "id": "client-6",
      "description": "NextGen Enterprises logo",
      "imageUrl": "https://images.unsplash.com/photo-1562705121-e624542c7b9b?crop=entropy&cs=tinysrgb&fit=max&fm=jpg&ixid=M3w3NDE5ODJ8MHwxfHNlYXJjaHwxMHx8Y29tcGFueSUyMGxvZ298ZW58MHx8fHwxNzY1NDI5MDQyfDA&ixlib=rb-4.1.0&q=80&w=1080",
      "imageHint": "company logo"
    },
    {
      "id": "client-7",
      "description": "Alpha Core logo",
      "imageUrl": "https://images.unsplash.com/photo-1549924231-f129b911e442?crop=entropy&cs=tinysrgb&fit=max&fm=jpg&ixid=M3w3NDE5ODJ8MHwxfHNlYXJjaHw3fHxjb21wYW55JTIwbG9nb3xlbnwwfHx8fDE3NjU0MjkwNDJ8MA&ixlib=rb-4.1.0&q=80&w=1080",
      "imageHint": "company logo"
    },
    {
      "id": "client-8",
      "description": "Zenith Group logo",
      "imageUrl": "https://images.unsplash.com/photo-1687523327554-fa9f50423489?crop=entropy&cs=tinysrgb&fit=max&fm=jpg&ixid=M3w3NDE5ODJ8MHwxfHNlYXJjaHw5fHxjb21wYW55JTIwbG9nb3xlbnwwfHx8fDE3NjU0MjkwNDJ8MA&ixlib=rb-4.1.0&q=80&w=1080",
      "imageHint": "company logo"
    },
    {
      "id": "testimonial-1",
      "description": "Photo of Jane Doe",
      "imageUrl": "https://images.unsplash.com/photo-1540569014015-19a7be504e3a?crop=entropy&cs=tinysrgb&fit=max&fm=jpg&ixid=M3w3NDE5ODJ8MHwxfHNlYXJjaHwyfHxwZXJzb24lMjBwb3J0cmFpdHxlbnwwfHx8fDE3NjUzNDA5MTh8MA&ixlib=rb-4.1.0&q=80&w=1080",
      "imageHint": "person portrait"
    },
    {
      "id": "testimonial-2",
      "description": "Photo of John Smith",
      "imageUrl": "https://images.unsplash.com/photo-1540569014015-19a7be504e3a?crop=entropy&cs=tinysrgb&fit=max&fm=jpg&ixid=M3w3NDE5ODJ8MHwxfHNlYXJjaHwyfHxwZXJzb24lMjBwb3J0cmFpdHxlbnwwfHx8fDE3NjUzNDA5MTh8MA&ixlib=rb-4.1.0&q=80&w=1080",
      "imageHint": "person portrait"
    },
    {
      "id": "testimonial-3",
      "description": "Photo of Emily White",
      "imageUrl": "https://images.unsplash.com/photo-1438761681033-6461ffad8d80?crop=entropy&cs=tinysrgb&fit=max&fm=jpg&ixid=M3w3NDE5ODJ8MHwxfHNlYXJjaHwzfHxwZXJzb24lMjBwb3J0cmFpdHxlbnwwfHx8fDE3NjUzNDA5MTh8MA&ixlib=rb-4.1.0&q=80&w=1080",
      "imageHint": "person portrait"
    }
  ]
}